dsrs_cli.py
dsrs_cli-0.1.1.dist-info/METADATA
dsrs_cli-0.1.1.dist-info/WHEEL
dsrs_cli-0.1.1.dist-info/entry_points.txt
dsrs_cli-0.1.1.dist-info/top_level.txt
dsrs_cli-0.1.1.dist-info/RECORD
