Metadata-Version: 2.4
Name: dsrs-cli
Version: 0.1.1
Summary: An interactive AI chatbot for the command line - DSRS
Home-page: https://github.com/fsaudm/dsrs-cli
Author: Farid Saud
Author-email: gfs3@illinois.edu
Classifier: Programming Language :: Python :: 3
Classifier: License :: OSI Approved :: MIT License
Classifier: Operating System :: OS Independent
Classifier: Environment :: Console
Classifier: Topic :: Utilities
Requires-Python: >=3.7
Requires-Dist: openai>=1.0
Requires-Dist: python-dotenv
Requires-Dist: rich
Requires-Dist: prompt-toolkit
Requires-Dist: tiktoken
Dynamic: author
Dynamic: author-email
Dynamic: classifier
Dynamic: description
Dynamic: description-content-type
Dynamic: home-page
Dynamic: requires-dist
Dynamic: requires-python
Dynamic: summary
